MANIFEST.in
README.rst
setup.py
pytlas_broker/__about__.py
pytlas_broker/__init__.py
pytlas_broker.egg-info/PKG-INFO
pytlas_broker.egg-info/SOURCES.txt
pytlas_broker.egg-info/dependency_links.txt
pytlas_broker.egg-info/entry_points.txt
pytlas_broker.egg-info/requires.txt
pytlas_broker.egg-info/top_level.txt
pytlas_broker/cli/__init__.py
pytlas_broker/cli/main.py
pytlas_broker/cli/repl.py
pytlas_broker/communicating/__init__.py
pytlas_broker/communicating/channel.py
pytlas_broker/communicating/mqtt.py
pytlas_broker/communicating/messages/__init__.py
pytlas_broker/communicating/messages/answer.py
pytlas_broker/communicating/messages/ask.py
pytlas_broker/communicating/messages/context.py
pytlas_broker/communicating/messages/done.py
pytlas_broker/communicating/messages/message.py
pytlas_broker/communicating/messages/parse.py
pytlas_broker/communicating/messages/ping.py
pytlas_broker/communicating/messages/pong.py
pytlas_broker/communicating/messages/thinking.py
pytlas_broker/conversing/__init__.py
pytlas_broker/conversing/client.py
pytlas_broker/conversing/model.py
pytlas_broker/conversing/server.py
pytlas_broker/conversing/agents/__init__.py
pytlas_broker/conversing/agents/factory.py
pytlas_broker/conversing/agents/from_file.py
tests/__init__.py
tests/communicating/__init__.py
tests/communicating/test_channel.py
tests/communicating/messages/__init__.py
tests/communicating/messages/test_messages.py
tests/conversing/__init__.py
tests/conversing/test_model.py
tests/conversing/test_server.py
tests/conversing/agents/__init__.py
tests/conversing/agents/test_from_file.py