Metadata-Version: 2.1
Name: pytlas-broker
Version: 1.0.0
Summary: Wrap the pytlas library across multiple channels
Home-page: https://github.com/atlassistant/pytlas-broker
Author: Julien LEICHER
Author-email: julien@leicher.me
License: GPL-3.0
Project-URL: Documentation, https://pytlas-broker.readthedocs.io/
Project-URL: Source, https://github.com/atlassistant/pytlas-broker
Project-URL: Tracker, https://github.com/atlassistant/pytlas-broker/issues
Platform: UNKNOWN
Classifier: Programming Language :: Python :: 3
Provides-Extra: test
